multipart_decoder/__init__.py
multipart_decoder/decoder.py
multipart_decoder-0.0.1.dist-info/licenses/LICENSE
multipart_decoder-0.0.1.dist-info/METADATA
multipart_decoder-0.0.1.dist-info/WHEEL
multipart_decoder-0.0.1.dist-info/top_level.txt
multipart_decoder-0.0.1.dist-info/RECORD
