Metadata-Version: 2.4
Name: multipart-decoder
Version: 0.0.1
Summary: A lightweight Python package for decoding multipart/form-data content
Author-email: Satya Tulasi Jalandhar C H <satyatulasijalandharch2@gmail.com>
License-Expression: MIT
Project-URL: Homepage, https://github.com/satyatulasijalandharch/multipart-decoder
Project-URL: Issues, https://github.com/satyatulasijalandharch/multipart-decoder/issues
Classifier: Programming Language :: Python :: 3
Classifier: Operating System :: OS Independent
Requires-Python: >=3.8
License-File: LICENSE
Dynamic: license-file
